README.md
CMakeLists.txt
MANIFEST.in
mmseqs/__init__.py
mmseqs/mmseqs_native.cpython-38-i386-linux-gnu.so
cmake/AppendTargetProperty.cmake
cmake/FindAtomic.cmake
cmake/MMseqsResourceCompiler.cmake
cmake/MMseqsSetupTest.cmake
cmake/FindMSan.cmake
cmake/MMseqsSetupDerivedTarget.cmake
cmake/xxdi.pl
cmake/FindTSan.cmake
cmake/FindASan.cmake
cmake/FindUBSan.cmake
cmake/GetGitRevisionDescription.cmake
cmake/CheckSSEFeatures.cmake
cmake/GetGitRevisionDescription.cmake.in
cmake/checkshell.sh
lib/pybind11/setup.py
lib/pybind11/.cmake-format.yaml
lib/pybind11/.pre-commit-config.yaml
lib/pybind11/.appveyor.yml
lib/pybind11/CMakeLists.txt
lib/pybind11/MANIFEST.in
lib/pybind11/.clang-tidy
lib/pybind11/README.rst
lib/pybind11/pyproject.toml
lib/pybind11/.gitignore
lib/pybind11/.readthedocs.yml
lib/pybind11/LICENSE
lib/pybind11/setup.cfg
lib/pybind11/pybind11/__init__.py
lib/pybind11/pybind11/commands.py
lib/pybind11/pybind11/_version.pyi
lib/pybind11/pybind11/_version.py
lib/pybind11/pybind11/__main__.py
lib/pybind11/pybind11/setup_helpers.py
lib/pybind11/pybind11/py.typed
lib/pybind11/pybind11/setup_helpers.pyi
lib/pybind11/tests/test_eigen.py
lib/pybind11/tests/test_numpy_vectorize.py
lib/pybind11/tests/test_methods_and_attributes.py
lib/pybind11/tests/test_enum.py
lib/pybind11/tests/test_chrono.cpp
lib/pybind11/tests/test_buffers.cpp
lib/pybind11/tests/test_exceptions.py
lib/pybind11/tests/test_async.cpp
lib/pybind11/tests/test_stl.cpp
lib/pybind11/tests/test_union.cpp
lib/pybind11/tests/test_tagbased_polymorphic.cpp
lib/pybind11/tests/test_virtual_functions.py
lib/pybind11/tests/test_kwargs_and_defaults.py
lib/pybind11/tests/pybind11_tests.cpp
lib/pybind11/tests/test_numpy_dtypes.py
lib/pybind11/tests/test_iostream.py
lib/pybind11/tests/test_operator_overloading.py
lib/pybind11/tests/test_eval.cpp
lib/pybind11/tests/test_gil_scoped.py
lib/pybind11/tests/test_opaque_types.cpp
lib/pybind11/tests/test_opaque_types.py
mmseqs-1.0.0.dist-info/RECORD
mmseqs-1.0.0.dist-info/WHEEL
mmseqs-1.0.0.dist-info/METADATA
