Metadata-Version: 2.1
Name: mmseqs
Version: 1.0.0
Summary: MMSEQS Python bindings
Author: Piotr Styczyński
Author-email: piotr@styczynski.in
Requires-Python: >=3.8,<4.0
Classifier: Programming Language :: Python :: 3
Classifier: Programming Language :: Python :: 3.8
Classifier: Programming Language :: Python :: 3.9
Requires-Dist: biopython (>=1.78,<2.0)
Requires-Dist: pandas (>=1.2.1,<2.0.0)
Requires-Dist: sqlitedict (>=1.7.0,<2.0.0)
